{
  "datasets": [
    {
      "name": "dataset_viz_9",
      "displayName": "HPX Retention Dataset",
      "asset_name": "workspace.default.mv_hpx_retention"
    }
  ],
  "pages": [
    {
      "name": "page_viz_9",
      "displayName": "0.5 HPX Retention",
      "layout": [
        {
          "widget": {
            "name": "hpx_retention_pivot_table",
            "queries": [
              {
                "name": "main_query",
                "query": {
                  "datasetName": "dataset_viz_9",
                  "fields": [
                    {
                      "name": "monthly_first_device_event_date_time",
                      "expression": "DATE_TRUNC('MONTH', `First Device Event Date Time`)"
                    },
                    {
                      "name": "months_since_first_use",
                      "expression": "`Months Since First Use`"
                    },
                    {
                      "name": "session_type",
                      "expression": "`Session Type`"
                    },
                    {
                      "name": "weeks_since_first_use",
                      "expression": "`Weeks Since First Use`"
                    },
                    {
                      "name": "active_devices",
                      "expression": "MEASURE(`Active Devices`)"
                    },
                    {
                      "name": "pct_devices_returning",
                      "expression": "MEASURE(`Active Devices`) / SUM(MEASURE(`Active Devices`)) OVER (PARTITION BY DATE_TRUNC('MONTH', `First Device Event Date Time`))"
                    }
                  ],
                  "disaggregated": false
                }
              }
            ],
            "spec": {
              "version": 3,
              "widgetType": "table",
              "encodings": {
                "columns": [
                  {
                    "fieldName": "monthly_first_device_event_date_time",
                    "displayName": "Month(First Device Event Date Time)"
                  },
                  {
                    "fieldName": "months_since_first_use",
                    "displayName": "Months Since First Use"
                  },
                  {
                    "fieldName": "session_type",
                    "displayName": "Session Type"
                  },
                  {
                    "fieldName": "weeks_since_first_use",
                    "displayName": "Weeks Since First Use"
                  },
                  {
                    "fieldName": "active_devices",
                    "displayName": "Active Devices"
                  },
                  {
                    "fieldName": "pct_devices_returning",
                    "displayName": "% Devices Returning"
                  }
                ]
              },
              "frame": {
                "showTitle": true,
                "title": "0.5 HPX Retention"
              }
            }
          },
          "position": {
            "x": 0,
            "y": 0,
            "width": 12,
            "height": 8
          }
        }
      ],
      "pageType": "PAGE_TYPE_CANVAS",
      "filters": []
    }
  ],
  "uiSettings": {
    "theme": {
      "widgetHeaderAlignment": "ALIGNMENT_UNSPECIFIED"
    }
  }
}